avc/__init__.py
avc/bytestrings.py
avc/cli.py
avc/core.py
avc/docx_utils.py
avc/file.py
avc/utils.py
pyavc-1.0.21.dist-info/licenses/LICENSE
pyavc-1.0.21.dist-info/METADATA
pyavc-1.0.21.dist-info/WHEEL
pyavc-1.0.21.dist-info/entry_points.txt
pyavc-1.0.21.dist-info/top_level.txt
pyavc-1.0.21.dist-info/RECORD
