Metadata-Version: 2.4
Name: pyavc
Version: 1.0.21
Summary: A command line utility and library for converting DOCX and TXT files to Avid Script Files (.avc)
Home-page: https://github.com/lawson-tanner/pyavc
Author: Lawson Tanner
Author-email: pyavc@lawsonia.cc
Classifier: Programming Language :: Python :: 3
Classifier: License :: OSI Approved :: MIT License
Classifier: Operating System :: OS Independent
Requires-Python: >=3.6
License-File: LICENSE
Requires-Dist: python-docx>=0.8.10
Dynamic: author
Dynamic: author-email
Dynamic: classifier
Dynamic: description
Dynamic: description-content-type
Dynamic: home-page
Dynamic: license-file
Dynamic: requires-dist
Dynamic: requires-python
Dynamic: summary
